waws/__init__.py
waws/bucket_manager.py
waws/instance_manager.py
waws/utils/__init__.py
waws/utils/configure.py
waws-0.0.0.4.data/scripts/waws
waws-0.0.0.4.dist-info/METADATA
waws-0.0.0.4.dist-info/RECORD
waws-0.0.0.4.dist-info/WHEEL
waws-0.0.0.4.dist-info/top_level.txt
