Metadata-Version: 2.1
Name: waws
Version: 0.0.0.4
Summary: Minimal AWS EC2/S3 wrapper by Wluper
Home-page: https://github.com/Wluper/waws
Author: Nikolai Rozanov
Author-email: nikolai@wluper.com
License: GPL 2.0
Platform: UNKNOWN
Requires-Dist: boto3
